spikeextractors/__init__.py
spikeextractors/baseextractor.py
spikeextractors/cacheextractors.py
spikeextractors/exceptions.py
spikeextractors/extraction_tools.py
spikeextractors/extractorlist.py
spikeextractors/multirecordingchannelextractor.py
spikeextractors/multirecordingtimeextractor.py
spikeextractors/multisortingextractor.py
spikeextractors/recordingextractor.py
spikeextractors/save_tools.py
spikeextractors/sortingextractor.py
spikeextractors/subrecordingextractor.py
spikeextractors/subsortingextractor.py
spikeextractors/testing.py
spikeextractors/version.py
spikeextractors/example_datasets/__init__.py
spikeextractors/example_datasets/synthesize_random_firings.py
spikeextractors/example_datasets/synthesize_random_waveforms.py
spikeextractors/example_datasets/synthesize_single_waveform.py
spikeextractors/example_datasets/synthesize_timeseries.py
spikeextractors/example_datasets/toy_example.py
spikeextractors/extractors/__init__.py
spikeextractors/extractors/alfsortingextractor/__init__.py
spikeextractors/extractors/alfsortingextractor/alfsortingextractor.py
spikeextractors/extractors/axonaunitrecordingextractor/__init__.py
spikeextractors/extractors/axonaunitrecordingextractor/axonaunitrecordingextractor.py
spikeextractors/extractors/bindatrecordingextractor/__init__.py
spikeextractors/extractors/bindatrecordingextractor/bindatrecordingextractor.py
spikeextractors/extractors/biocamrecordingextractor/__init__.py
spikeextractors/extractors/biocamrecordingextractor/biocamrecordingextractor.py
spikeextractors/extractors/cedextractors/__init__.py
spikeextractors/extractors/cedextractors/cedrecordingextractor.py
spikeextractors/extractors/cedextractors/utils.py
spikeextractors/extractors/cellexplorersortingextractor/__init__.py
spikeextractors/extractors/cellexplorersortingextractor/cellexplorersortingextractor.py
spikeextractors/extractors/combinatosortingextractor/__init__.py
spikeextractors/extractors/combinatosortingextractor/combinatosortingextractor.py
spikeextractors-0.9.11.dist-info/LICENSE
spikeextractors-0.9.11.dist-info/METADATA
spikeextractors-0.9.11.dist-info/WHEEL
spikeextractors-0.9.11.dist-info/top_level.txt
spikeextractors-0.9.11.dist-info/RECORD
